pytest_result_log/plugin.cpython-312-x86_64-linux-musl.so
pytest_result_log/__init__.cpython-312-x86_64-linux-musl.so
pytest_result_log/const.cpython-312-x86_64-linux-musl.so
pytest_result_log/hooks.cpython-312-x86_64-linux-musl.so
pytest_result_log-1.3.0.dist-info/METADATA
pytest_result_log-1.3.0.dist-info/WHEEL
pytest_result_log-1.3.0.dist-info/RECORD
pytest_result_log-1.3.0.dist-info/entry_points.txt
