Metadata-Version: 2.1
Name: pytest-result-log
Version: 1.3.0
Summary: A pytest plugin that records the start, end, and result information of each use case in a log file
License: Apache-2.0
Author-email: dongfangtianyu <7629022+dongfangtianyu@users.noreply.github.com>
Requires-Python: >=3.10.6
Requires-Dist: pytest>=7.2.0
Project-URL: Homepage, https://github.com/dongfangtianyu/pytest_result_log
